bpmappers/__init__.py
bpmappers/djangomodel.py
bpmappers/exceptions.py
bpmappers/fields.py
bpmappers/mappers.py
bpmappers/utils.py
bpmappers-1.3.dist-info/LICENSE
bpmappers-1.3.dist-info/METADATA
bpmappers-1.3.dist-info/WHEEL
bpmappers-1.3.dist-info/top_level.txt
bpmappers-1.3.dist-info/RECORD
