Metadata-Version: 2.1
Name: bpmappers
Version: 1.3
Summary: bpmappers is a Python moudle that maps Python dictionary values and object properties to different dictionary.
Home-page: https://bpmappers.readthedocs.io/ja/stable/
Author: BeProud Inc.
Author-email: tokibito@gmail.com
License: MIT License
Keywords: model,mapper,django
Platform: UNKNOWN
Classifier: Development Status :: 5 - Production/Stable
Classifier: Environment :: Plugins
Classifier: Framework :: Django
Classifier: Intended Audience :: Developers
Classifier: License :: OSI Approved :: MIT License
Classifier: Programming Language :: Python
Classifier: Programming Language :: Python :: 3.6
Classifier: Programming Language :: Python :: 3.7
Classifier: Programming Language :: Python :: 3.8
Classifier: Programming Language :: Python :: 3.9
Classifier: Topic :: Software Development :: Libraries :: Python Modules
Provides-Extra: django
Provides-Extra: develop
